botw_flag_util/__init__.py
botw_flag_util/__main__.py
botw_flag_util/__version__.py
botw_flag_util/finder.py
botw_flag_util/flag.py
botw_flag_util/generator.py
botw_flag_util/store.py
botw_flag_util/util.py
botw_flag_util/data/overrides.json
botw_flag_util/data/vanilla_actors.json
botw_flag_util/data/vanilla_hash.json
botw_flag_util/data/vanilla_shrines.json
botw_flag_util-0.3.8.dist-info/LICENSE
botw_flag_util-0.3.8.dist-info/METADATA
botw_flag_util-0.3.8.dist-info/WHEEL
botw_flag_util-0.3.8.dist-info/entry_points.txt
botw_flag_util-0.3.8.dist-info/top_level.txt
botw_flag_util-0.3.8.dist-info/RECORD
