Metadata-Version: 2.1
Name: botw_flag_util
Version: 0.3.8
Summary: Game data and save game data flag utilities for LoZ:BotW
Home-page: https://github.com/GingerAvalanche/botw_flag_util
Author: Ginger
Author-email: chodness@gmail.com
Classifier: Programming Language :: Python :: 3.7
Classifier: License :: OSI Approved :: GNU Affero General Public License v3 or later (AGPLv3+)
Classifier: Operating System :: OS Independent
Classifier: Development Status :: 4 - Beta
Requires-Python: >=3.7.4
License-File: LICENSE
Requires-Dist: bcml >=3.0.0b25
Requires-Dist: oead >=0.11.2
